xaal/__init__.py
xaal/homekit/__init__.py
xaal/homekit/__main__.py
xaal/homekit/accessories.py
xaal/homekit/gw.py
xaal_homekit-0.2.2.dist-info/METADATA
xaal_homekit-0.2.2.dist-info/WHEEL
xaal_homekit-0.2.2.dist-info/top_level.txt
xaal_homekit-0.2.2.dist-info/RECORD
