Metadata-Version: 2.4
Name: xaal.homekit
Version: 0.2.2
Summary: xAAL devices for Homekit
Author-email: Jerome Kerdreux <Jerome.Kerdreux@imt-atlantique.fr>
License-Expression: GPL-3.0-or-later
Project-URL: Homepage, https://recherche.imt-atlantique.fr/xaal/
Project-URL: Documentation, https://gitlab.imt-atlantique.fr/xaal/code/python/-/blob/main/devices/protocols/HomeKit/README.rst
Project-URL: Source, https://gitlab.imt-atlantique.fr/xaal/code/python/-/tree/main/devices/protocols/HomeKit
Keywords: xaal,homekit
Classifier: Programming Language :: Python
Classifier: Topic :: Home Automation
Requires-Dist: xaal.lib
Requires-Dist: aiohomekit
